<annotation>
	<folder></folder>
	<filename>2008_000857_jpg.rf.a3609f8028bf6e3178727237a1f5ee6e.jpg</filename>
	<path>2008_000857_jpg.rf.a3609f8028bf6e3178727237a1f5ee6e.jpg</path>
	<source>
		<database>roboflow.com</database>
	</source>
	<size>
		<width>640</width>
		<height>640</height>
		<depth>3</depth>
	</size>
	<segmented>0</segmented>
	<object>
		<name>sofa</name>
		<pose>Unspecified</pose>
		<truncated>0</truncated>
		<difficult>0</difficult>
		<occluded>0</occluded>
		<bndbox>
			<xmin>395</xmin>
			<xmax>637</xmax>
			<ymin>223</ymin>
			<ymax>438</ymax>
		</bndbox>
	</object>
	<object>
		<name>pottedplant</name>
		<pose>Unspecified</pose>
		<truncated>0</truncated>
		<difficult>0</difficult>
		<occluded>0</occluded>
		<bndbox>
			<xmin>355</xmin>
			<xmax>461</xmax>
			<ymin>160</ymin>
			<ymax>278</ymax>
		</bndbox>
	</object>
</annotation>
