<annotation>
	<folder></folder>
	<filename>2008_000666_jpg.rf.101e996afe0d420c8e4f16a7dc62958b.jpg</filename>
	<path>2008_000666_jpg.rf.101e996afe0d420c8e4f16a7dc62958b.jpg</path>
	<source>
		<database>roboflow.com</database>
	</source>
	<size>
		<width>640</width>
		<height>640</height>
		<depth>3</depth>
	</size>
	<segmented>0</segmented>
	<object>
		<name>person</name>
		<pose>Unspecified</pose>
		<truncated>0</truncated>
		<difficult>0</difficult>
		<occluded>0</occluded>
		<bndbox>
			<xmin>329</xmin>
			<xmax>453</xmax>
			<ymin>253</ymin>
			<ymax>608</ymax>
		</bndbox>
	</object>
</annotation>
